snapper/__init__.py
snapper/__main__.py
snapper/core.py
snapper/classes/__init__.py
snapper/classes/splicegraph.py
snapper/classes/transcript.py
snapper/classes/treader.py
snapper/classes/txgroup.py
snapper/utils/__init__.py
snapper/utils/common.py
snapper_av-1.0.2.dist-info/licenses/LICENSE
tests/__init__.py
tests/tests.py
snapper_av-1.0.2.dist-info/METADATA
snapper_av-1.0.2.dist-info/WHEEL
snapper_av-1.0.2.dist-info/entry_points.txt
snapper_av-1.0.2.dist-info/top_level.txt
snapper_av-1.0.2.dist-info/RECORD
