Metadata-Version: 2.4
Name: snapper-av
Version: 1.0.2
Summary: SNAPPER: Correct Intron Shifts in Alignments via Reference Annotation
Home-page: https://github.com/alevar/snapper
Author: Ales Varabyou
Author-email: ales.varabyou@jhu.edu
License: GPLv3
Classifier: Programming Language :: Python :: 3
Classifier: License :: OSI Approved :: GNU General Public License v3 (GPLv3)
Classifier: Operating System :: OS Independent
Requires-Python: >=3.6
License-File: LICENSE
Requires-Dist: biopython
Requires-Dist: intervaltree
Requires-Dist: numpy
Requires-Dist: pyfaidx
Requires-Dist: pysam
Requires-Dist: setuptools
Dynamic: author
Dynamic: author-email
Dynamic: classifier
Dynamic: description
Dynamic: description-content-type
Dynamic: home-page
Dynamic: license
Dynamic: license-file
Dynamic: requires-dist
Dynamic: requires-python
Dynamic: summary
